llmsmith/__init__.py
llmsmith/agent/__init__.py
llmsmith/agent/errors.py
llmsmith/agent/function/__init__.py
llmsmith/agent/function/cohere.py
llmsmith/agent/function/gemini.py
llmsmith/agent/function/groq.py
llmsmith/agent/function/openai.py
llmsmith/agent/function/options/__init__.py
llmsmith/agent/function/options/openai.py
llmsmith/agent/tool/__init__.py
llmsmith/agent/tool/cohere.py
llmsmith/agent/tool/gemini.py
llmsmith/agent/tool/groq.py
llmsmith/agent/tool/openai.py
llmsmith/job/__init__.py
llmsmith/job/base.py
llmsmith/job/job.py
llmsmith/reranker/__init__.py
llmsmith/reranker/base.py
llmsmith/reranker/cohere.py
llmsmith/reranker/options/__init__.py
llmsmith/reranker/options/cohere.py
llmsmith/task/__init__.py
llmsmith/task/base.py
llmsmith/task/models.py
llmsmith/task/retrieval/__init__.py
llmsmith/task/retrieval/vector/__init__.py
llmsmith/task/retrieval/vector/base.py
llmsmith/task/retrieval/vector/chromadb.py
llmsmith/task/retrieval/vector/options/__init__.py
llmsmith/task/retrieval/vector/options/chromadb.py
llmsmith/task/retrieval/vector/options/pgvector.py
llmsmith/task/retrieval/vector/options/pinecone.py
llmsmith/task/retrieval/vector/options/qdrant.py
llmsmith/task/retrieval/vector/pgvector.py
llmsmith/task/retrieval/vector/pinecone.py
llmsmith/task/retrieval/vector/qdrant.py
llmsmith/task/textgen/__init__.py
llmsmith/task/textgen/claude.py
llmsmith/task/textgen/cohere.py
llmsmith/task/textgen/errors.py
llmsmith/task/textgen/gemini.py
llmsmith/task/textgen/groq.py
llmsmith/task/textgen/openai.py
llmsmith/task/textgen/options/__init__.py
llmsmith/task/textgen/options/claude.py
llmsmith/task/textgen/options/cohere.py
llmsmith/task/textgen/options/gemini.py
llmsmith/task/textgen/options/groq.py
llmsmith/task/textgen/options/openai.py
llmsmith-0.8.0.dist-info/LICENSE
llmsmith-0.8.0.dist-info/METADATA
llmsmith-0.8.0.dist-info/WHEEL
llmsmith-0.8.0.dist-info/RECORD
