Metadata-Version: 2.1
Name: LLMSmith
Version: 0.8.0
Summary: Lightweight Python library designed for developing functionalities powered by Large Language Models (LLMs)
Author: Dheeraj Gopinath
Author-email: dheeraj.gopinath@gmail.com
Requires-Python: >=3.9,<3.13
Classifier: Development Status :: 2 - Pre-Alpha
Classifier: Intended Audience :: Developers
Classifier: License :: OSI Approved :: MIT License
Classifier: Programming Language :: Python :: 3
Classifier: Programming Language :: Python :: 3.9
Classifier: Programming Language :: Python :: 3.10
Classifier: Programming Language :: Python :: 3.11
Classifier: Programming Language :: Python :: 3.12
Classifier: Topic :: Scientific/Engineering :: Artificial Intelligence
Classifier: Topic :: Software Development :: Libraries :: Python Modules
Provides-Extra: all
Provides-Extra: chromadb
Provides-Extra: claude
Provides-Extra: cohere
Provides-Extra: gemini
Provides-Extra: groq
Provides-Extra: openai
Provides-Extra: pgvector
Provides-Extra: pinecone
Provides-Extra: qdrant
Requires-Dist: anthropic (>=0.19.2,<0.20.0) ; extra == "claude" or extra == "all"
Requires-Dist: chromadb-client (>=0.4.25.dev0,<0.5.0) ; extra == "chromadb" or extra == "all"
Requires-Dist: cohere (>=5.3.2,<6.0.0) ; extra == "cohere" or extra == "all"
Requires-Dist: google-generativeai (>=0.4.0,<0.5.0) ; extra == "gemini" or extra == "all"
Requires-Dist: groq (>=0.6.0,<0.7.0) ; extra == "groq" or extra == "all"
Requires-Dist: onnxruntime (>=1.17.1,<2.0.0) ; extra == "chromadb" or extra == "all"
Requires-Dist: openai (>=1.23.2,<2.0.0) ; extra == "openai" or extra == "all"
Requires-Dist: pgvector (>=0.2.5,<0.3.0) ; extra == "pgvector" or extra == "all"
Requires-Dist: pinecone-client (>=4.1.0,<5.0.0) ; extra == "pinecone" or extra == "all"
Requires-Dist: protobuf (==3.20.3) ; extra == "chromadb" or extra == "all"
Requires-Dist: psycopg (>=3.1.19,<4.0.0) ; extra == "pgvector" or extra == "all"
Requires-Dist: python-dotenv (>=1.0.1,<2.0.0)
Requires-Dist: qdrant-client (>=1.8.2,<2.0.0) ; extra == "qdrant" or extra == "all"
Requires-Dist: sqlalchemy[asyncio] (>=2.0.30,<3.0.0) ; extra == "pgvector" or extra == "all"
Requires-Dist: tokenizers (>=0.15.2,<0.16.0) ; extra == "chromadb" or extra == "all"
